protocol_lib/__init__.py
protocol_lib/collection.py
protocol_lib/container.py
protocol_lib/hashable.py
protocol_lib/iterable.py
protocol_lib/mapping.py
protocol_lib/py.typed
protocol_lib/sequence.py
protocol_lib/sized.py
protocol_lib-1.0.0.dist-info/LICENSE
protocol_lib-1.0.0.dist-info/WHEEL
protocol_lib-1.0.0.dist-info/METADATA
protocol_lib-1.0.0.dist-info/RECORD
