Metadata-Version: 2.1
Name: protocol-lib
Version: 1.0.0
Summary: Protocols for better structural typing
Home-page: https://github.com/eganjs/protocol-lib
License: MIT
Author: Joseph Egan
Author-email: joseph.s.egan@gmail.com
Requires-Python: >=3.6,<4.0
Classifier: License :: OSI Approved :: MIT License
Classifier: Programming Language :: Python :: 3
Classifier: Programming Language :: Python :: 3.6
Classifier: Programming Language :: Python :: 3.7
Classifier: Programming Language :: Python :: 3.8
Classifier: Programming Language :: Python :: 3.9
Requires-Dist: typing-extensions (>=3.7.4.3,<4.0.0.0)
Project-URL: Repository, https://github.com/eganjs/protocol-lib
